dogdorm/__init__.py
dogdorm/main.py
dogdorm-1.0.0.dist-info/licenses/LICENSE
dogdorm-1.0.0.dist-info/METADATA
dogdorm-1.0.0.dist-info/WHEEL
dogdorm-1.0.0.dist-info/top_level.txt
dogdorm-1.0.0.dist-info/RECORD
