Metadata-Version: 2.4
Name: dogdorm
Version: 1.0.0
Summary: monitor stun and other servers
Home-page: http://github.com/robertsdotpm/dogdorm
Author: Matthew Roberts
Author-email: matthew@roberts.pm
License: MIT
Keywords: STUN TURN MQTT NTP server monitor
Classifier: Intended Audience :: Developers
Classifier: Programming Language :: Python :: 3
License-File: LICENSE
Requires-Dist: fastapi
Dynamic: author
Dynamic: author-email
Dynamic: classifier
Dynamic: description
Dynamic: description-content-type
Dynamic: home-page
Dynamic: keywords
Dynamic: license
Dynamic: license-file
Dynamic: requires-dist
Dynamic: summary
